HiggsML/__init__.py
HiggsML/__version__.py
HiggsML/datasets.py
HiggsML/derived_quantities.py
HiggsML/ingestion.py
HiggsML/run_competition.py
HiggsML/score.py
HiggsML/systematics.py
HiggsML/visualization.py
higgsml-0.1.5.dist-info/METADATA
higgsml-0.1.5.dist-info/WHEEL
higgsml-0.1.5.dist-info/licenses/LICENSE
higgsml-0.1.5.dist-info/RECORD
