Metadata-Version: 2.4
Name: HiggsML
Version: 0.1.5
Summary: A Black Swan package
Project-URL: Homepage, https://github.com/blackSwanCS/black_swan_pkg
Project-URL: Issues, https://github.com/blackSwanCS/black_swan_pkg/issues
Project-URL: Documentation, https://black-swan-pkg.readthedocs.io/en/latest
Author-email: Ragansu Chakkappai <ragansu.chakkappai@universite-paris-saclay.fr>, David Rousseau <david.rousseau@uijclab.in2p3.fr>, "V. Estrade" <v.estrade@centralesupelec.fr>, Ihsan Ullah <ihsan.ullah@universite-paris-saclay.fr>
License-File: LICENSE
Classifier: License :: OSI Approved :: MIT License
Classifier: Operating System :: OS Independent
Classifier: Programming Language :: Python :: 3
Requires-Python: >=3.7
Requires-Dist: argparse>=1.4.0
Requires-Dist: matplotlib>=3.8.0
Requires-Dist: mpld3>=0.5.8
Requires-Dist: numpy>=1.26.4
Requires-Dist: pandas>=2.2.2
Requires-Dist: pyarrow>=15.0.0
Requires-Dist: requests>=2.31.0
Requires-Dist: scikit-learn>=1.4.2
Requires-Dist: seaborn>=0.13.1
Requires-Dist: tabulate>=0.9.0
